dishka_faststream/__init__.py
dishka_faststream/_version.py
dishka_faststream/faststream.py
dishka_faststream/py.typed
dishka_faststream-0.6.0.dist-info/METADATA
dishka_faststream-0.6.0.dist-info/WHEEL
dishka_faststream-0.6.0.dist-info/licenses/LICENSE
dishka_faststream-0.6.0.dist-info/RECORD
