Metadata-Version: 2.4
Name: dishka-faststream
Version: 0.6.0
Summary: Integration package for Dishka DI and FastStream framework
Project-URL: Source, https://github.com/faststream-community/dishka-faststream
Project-URL: Homepage, https://github.com/faststream-community/dishka-faststream
Project-URL: Tracker, https://github.com/faststream-community/dishka-faststream/issues
Author-email: Nikita Pastukhov <nikita@pastukhov-dev.com>
License-Expression: Apache-2.0
License-File: LICENSE
Classifier: Intended Audience :: Developers
Classifier: License :: OSI Approved :: Apache Software License
Classifier: Operating System :: OS Independent
Classifier: Programming Language :: Python :: 3.10
Classifier: Programming Language :: Python :: 3.11
Classifier: Programming Language :: Python :: 3.12
Classifier: Programming Language :: Python :: 3.13
Classifier: Programming Language :: Python :: 3.14
Classifier: Topic :: Software Development :: Libraries
Classifier: Typing :: Typed
Requires-Python: >=3.10
Requires-Dist: dishka<2,>=1.7
Requires-Dist: faststream<0.7,>=0.6
